commonhealth_storage_client/__init__.py
commonhealth_storage_client/client.py
commonhealth_storage_client/crypto.py
commonhealth_storage_client/errors.py
commonhealth_storage_client/jwt.py
commonhealth_storage_client/sqlite_delegate.py
commonhealth_storage_client-0.0.1.dist-info/LICENSE
commonhealth_storage_client-0.0.1.dist-info/METADATA
commonhealth_storage_client-0.0.1.dist-info/WHEEL
commonhealth_storage_client-0.0.1.dist-info/top_level.txt
commonhealth_storage_client-0.0.1.dist-info/RECORD
