Metadata-Version: 2.1
Name: commonhealth-storage-client
Version: 0.0.1
Summary: TODO
Home-page: https://github.com/the-commons-project/chcs-python-client
Author: The Commons Project Foundation
Author-email: developers@commonhealth.org
License: UNKNOWN
Project-URL: Bug Tracker, https://github.com/the-commons-project/chcs-python-client/issues
Platform: UNKNOWN
Classifier: Programming Language :: Python :: 3
Classifier: License :: OSI Approved :: MIT License
Classifier: Operating System :: OS Independent
Requires-Python: >=3.6
License-File: LICENSE
Requires-Dist: cryptography (==36.0.0)
Requires-Dist: requests (==2.26.0)
Requires-Dist: tink (==1.6.1)
